{"height":600,"width":9000,"entities":[{"type":"box","y":0.53999996,"size":1.0,"x":9.32},{"number":1,"type":"player","y":0.97999954,"x":3.8},{"number":2,"type":"player","y":0.8199997,"x":2.06},{"type":"boxitem","y":0.53999996,"x":14.44},{"grassType":0,"type":"grass","y":0.19999981,"x":10.26},{"grassType":0,"type":"grass","y":0.19999981,"x":10.8},{"grassType":0,"type":"grass","y":0.19999981,"x":10.52},{"grassType":0,"type":"grass","y":0.19999981,"x":11.06},{"treeType":0,"type":"tree","y":1.9799995,"x":11.82},{"type":"box","y":0.6199999,"size":1.0,"x":21.14},{"type":"box","y":0.5799999,"size":1.0,"x":22.36},{"shrubType":0,"type":"shrub","y":0.3199997,"x":12.84},{"shrubType":0,"type":"shrub","y":0.3199997,"x":13.48},{"shrubType":0,"type":"shrub","y":0.3199997,"x":18.78},{"shrubType":0,"type":"shrub","y":0.3199997,"x":17.96},{"treeType":0,"type":"tree","y":1.8999996,"x":20.18},{"treeType":0,"type":"tree","y":1.9399996,"x":27.28},{"treeType":0,"type":"tree","y":1.9399996,"x":30.0},{"treeType":0,"type":"tree","y":1.9399996,"x":37.54},{"treeType":0,"type":"tree","y":1.9399996,"x":44.98},{"treeType":0,"type":"tree","y":1.9399996,"x":50.92},{"treeType":0,"type":"tree","y":1.9399996,"x":58.36},{"height":1.0,"density":1.0,"width":4.0,"type":"water","y":-0.6000004,"x":41.32},{"height":1.0,"density":1.0,"width":4.0,"type":"water","y":-0.64000034,"x":33.4},{"grassType":0,"type":"grass","y":0.15999985,"x":28.04},{"grassType":0,"type":"grass","y":0.15999985,"x":28.32},{"shrubType":0,"type":"shrub","y":0.23999977,"x":30.36},{"shrubType":0,"type":"shrub","y":0.23999977,"x":36.6},{"shrubType":0,"type":"shrub","y":0.27999973,"x":37.6},{"shrubType":0,"type":"shrub","y":0.23999977,"x":47.04},{"shrubType":0,"type":"shrub","y":0.23999977,"x":49.48},{"type":"box","y":0.46000004,"size":1.0,"x":61.2},{"type":"box","y":0.46000004,"size":1.0,"x":62.28},{"type":"box","y":1.46,"size":1.0,"x":61.22},{"type":"box","y":1.46,"size":1.0,"x":62.26},{"type":"box","y":2.46,"size":1.0,"x":61.68},{"hitsUntilBreak":0.0,"height":0.0,"width":0.0,"type":"breakable","y":0.85999966,"x":70.08},{"type":"box","y":0.6199999,"size":1.0,"x":71.06},{"hitsUntilBreak":0.0,"height":0.0,"width":0.0,"type":"breakable","y":1.5799999,"x":72.08},{"shrubType":0,"type":"shrub","y":0.27999973,"x":74.7},{"shrubType":0,"type":"shrub","y":0.3199997,"x":75.68},{"shrubType":0,"type":"shrub","y":0.23999977,"x":64.72},{"shrubType":0,"type":"shrub","y":0.23999977,"x":67.58},{"treeType":0,"type":"tree","y":1.9799995,"x":71.12},{"treeType":0,"type":"tree","y":1.9399996,"x":78.18},{"treeType":0,"type":"tree","y":1.8599997,"x":90.6},{"height":1.0,"density":1.0,"width":10.0,"type":"water","y":-0.64000034,"x":84.12},{"grassType":0,"type":"grass","y":0.15999985,"x":91.56},{"height":0.15,"width":3.0,"type":"oneway_wall","y":1.6,"x":15.8},{"height":0.15,"width":3.0,"type":"oneway_wall","y":1.6,"x":22.88},{"grassType":0,"type":"grass","y":0.15999985,"x":91.1},{"grassType":0,"type":"grass","y":0.15999985,"x":92.02},{"treeType":0,"type":"tree","y":1.8999996,"x":95.34},{"grassType":0,"type":"grass","y":0.15999985,"x":99.16},{"grassType":0,"type":"grass","y":0.15999985,"x":99.54},{"grassType":0,"type":"grass","y":0.15999985,"x":99.92},{"grassType":0,"type":"grass","y":0.14000034,"x":101.44},{"grassType":0,"type":"grass","y":0.14000034,"x":102.5},{"grassType":0,"type":"grass","y":0.19999981,"x":103.34},{"grassType":0,"type":"grass","y":0.1800003,"x":105.68},{"hitsUntilBreak":1.0,"height":5.5,"width":0.4,"type":"breakable","y":2.7600002,"x":104.66},{"type":"box","y":0.46000004,"size":1.0,"x":106.28},{"type":"box","y":0.5,"size":1.0,"x":107.36},{"type":"box","y":0.5,"size":1.0,"x":108.54},{"type":"box","y":1.46,"size":1.0,"x":106.68},{"type":"box","y":1.4799995,"size":1.0,"x":107.92},{"type":"box","y":0.47999954,"size":1.0,"x":109.66},{"type":"box","y":0.5,"size":1.0,"x":110.96},{"type":"box","y":6.06,"size":1.0,"x":104.68},{"type":"box","y":0.5,"size":1.0,"x":101.66},{"treeType":0,"type":"tree","y":1.8999996,"x":120.66},{"treeType":0,"type":"tree","y":1.8999996,"x":132.84},{"treeType":0,"type":"tree","y":1.8800001,"x":146.48},{"treeType":0,"type":"tree","y":1.8599997,"x":158.5},{"treeType":0,"type":"tree","y":1.9200001,"x":170.22},{"shrubType":0,"type":"shrub","y":0.22000027,"x":163.22},{"shrubType":0,"type":"shrub","y":0.19999981,"x":168.76},{"type":"boxitem","y":-0.020000458,"x":33.34},{"type":"boxitem","y":0.53999996,"x":46.24},{"type":"boxitem","y":3.46,"x":61.68},{"type":"boxitem","y":-0.03999996,"x":83.42},{"type":"finalflag","y":0.27999973,"x":176.28}]}
